contflame/__init__.py
contflame/internals.py
contflame/data/__init__.py
contflame/data/datasets.py
contflame/data/utils.py
continual_flame-1.0.dist-info/LICENSE
continual_flame-1.0.dist-info/METADATA
continual_flame-1.0.dist-info/WHEEL
continual_flame-1.0.dist-info/top_level.txt
continual_flame-1.0.dist-info/RECORD
