Metadata-Version: 2.1
Name: continual-flame
Version: 1.0
Summary: A continual learning PyTorch package
Home-page: https://github.com/andrew-r96/ContinualFlame
Author: Andrea Rosasco
Author-email: andrearosasco.ar@gmail.com
License: UNKNOWN
Platform: UNKNOWN
Classifier: Programming Language :: Python :: 3
Classifier: License :: OSI Approved :: GNU General Public License v3 (GPLv3)
Classifier: Operating System :: OS Independent
Classifier: Topic :: Scientific/Engineering :: Artificial Intelligence
Requires-Python: >=3.8
